splogger/__init__.py
splogger/loggers.py
simplepylogg3r-1.5.1.dist-info/LICENSE
simplepylogg3r-1.5.1.dist-info/METADATA
simplepylogg3r-1.5.1.dist-info/WHEEL
simplepylogg3r-1.5.1.dist-info/top_level.txt
simplepylogg3r-1.5.1.dist-info/RECORD
